pyperms/__init__.py
pyperms/builder.py
pyperms/conditions/__init__.py
pyperms/conditions/attribute.py
pyperms/conditions/base.py
pyperms/conditions/operators.py
pyperms/conditions/types.py
pyperms/conditions/utils.py
pyperms/permissions.py
pyperms/py.typed
pyperms/rule.py
pyperms/types.py
pyperms-0.1.0.dist-info/LICENSE
pyperms-0.1.0.dist-info/METADATA
pyperms-0.1.0.dist-info/WHEEL
pyperms-0.1.0.dist-info/RECORD
