Metadata-Version: 2.1
Name: pyperms
Version: 0.1.0
Summary: Library for convenient access control
Home-page: https://github.com/X-AROK/pyperms
License: MIT
Keywords: pyperms,permissions,casl,ability
Author: X-AROK
Author-email: an_xarok@mail.ru
Requires-Python: >=3.8,<4.0
Classifier: Intended Audience :: Information Technology
Classifier: Intended Audience :: System Administrators
Classifier: License :: OSI Approved :: MIT License
Classifier: Operating System :: OS Independent
Classifier: Programming Language :: Python
Classifier: Programming Language :: Python :: 3
Classifier: Programming Language :: Python :: 3.8
Classifier: Programming Language :: Python :: 3.9
Classifier: Programming Language :: Python :: 3.10
Classifier: Programming Language :: Python :: 3.11
Classifier: Programming Language :: Python :: 3 :: Only
Classifier: Topic :: Software Development
Classifier: Topic :: Software Development :: Libraries
Classifier: Topic :: Software Development :: Libraries :: Python Modules
Classifier: Typing :: Typed
Project-URL: Repository, https://github.com/X-AROK/pyperms
